[
  {
    "id": "CARD-001",
    "title": "회의 중 의견 충돌",
    "situation": "팀 회의에서 당신의 의견과 선배의 의견이 정면으로 충돌했습니다. 선배는 기존 방식을 고수하려 하고, 당신은 새로운 접근법이 더 효율적이라고 생각합니다. 다른 팀원들은 눈치를 보며 침묵하고 있습니다.",
    "choices": [
      {"id": "A", "text": "선배의 경험을 존중하며 일단 따르고, 나중에 따로 의견을 제시한다.", "score": 80},
      {"id": "B", "text": "데이터와 근거를 들어 내 의견을 논리적으로 설명한다.", "score": 100},
      {"id": "C", "text": "다른 팀원들의 의견을 먼저 구해서 다수결로 결정하자고 제안한다.", "score": 90}
    ],
    "learningPoint": "의견 충돌 상황에서 감정을 배제하고 논리적으로 소통하는 것이 중요합니다."
  },
  {
    "id": "CARD-002",
    "title": "급한 업무 요청",
    "situation": "퇴근 30분 전, 팀장님이 오늘 중으로 완료해야 하는 급한 업무를 요청했습니다. 이미 오늘 저녁에 중요한 약속이 있습니다.",
    "choices": [
      {"id": "A", "text": "약속을 취소하고 업무를 완료한다.", "score": 80},
      {"id": "B", "text": "상황을 설명하고 내일 아침 일찍 처리해도 되는지 협의한다.", "score": 100},
      {"id": "C", "text": "동료에게 도움을 요청해 함께 빠르게 처리한다.", "score": 90}
    ],
    "learningPoint": "워라밸과 업무 책임 사이의 균형을 어떻게 맞출지 고민이 필요합니다."
  },
  {
    "id": "CARD-003",
    "title": "동료의 실수 발견",
    "situation": "중요한 보고서에서 동료의 실수를 발견했습니다. 보고서는 곧 경영진에게 제출될 예정이고, 동료는 지금 휴가 중입니다.",
    "choices": [
      {"id": "A", "text": "직접 수정해서 보고서를 완성한다.", "score": 90},
      {"id": "B", "text": "팀장님께 상황을 보고하고 지시를 따른다.", "score": 100},
      {"id": "C", "text": "동료에게 연락해서 상황을 알리고 어떻게 할지 의논한다.", "score": 80}
    ],
    "learningPoint": "팀워크와 개인 책임 사이에서 적절한 판단이 필요합니다."
  },
  {
    "id": "CARD-004",
    "title": "고객 불만 대응",
    "situation": "화가 난 고객이 전화로 강하게 항의하고 있습니다. 고객의 불만은 타 부서의 실수 때문이지만, 고객은 당신에게 해결을 요구하고 있습니다.",
    "choices": [
      {"id": "A", "text": "먼저 고객의 이야기를 끝까지 경청하고 공감을 표현한다.", "score": 100},
      {"id": "B", "text": "타 부서 담당자에게 바로 연결해드리겠다고 안내한다.", "score": 80},
      {"id": "C", "text": "고객의 연락처를 받고 확인 후 콜백하겠다고 약속한다.", "score": 90}
    ],
    "learningPoint": "고객 응대에서는 먼저 공감하고, 그 다음 해결책을 제시하는 것이 효과적입니다."
  },
  {
    "id": "CARD-005",
    "title": "프로젝트 일정 지연",
    "situation": "담당하고 있는 프로젝트의 일정이 예상보다 2주 지연될 것 같습니다. 아직 팀장님께 보고하지 않았습니다.",
    "choices": [
      {"id": "A", "text": "즉시 팀장님께 보고하고 해결 방안을 함께 논의한다.", "score": 100},
      {"id": "B", "text": "야근과 주말 근무로 일정을 맞추려고 노력한다.", "score": 80},
      {"id": "C", "text": "지연 사유와 복구 계획을 정리한 후 보고한다.", "score": 90}
    ],
    "learningPoint": "문제 발생 시 빠른 보고와 함께 해결책을 제시하는 것이 신뢰를 쌓는 방법입니다."
  },
  {
    "id": "CARD-006",
    "title": "팀원 간 갈등",
    "situation": "같은 팀의 두 동료가 업무 방식 차이로 갈등을 겪고 있습니다. 둘 다 당신에게 각자의 편을 들어달라고 합니다.",
    "choices": [
      {"id": "A", "text": "어느 편도 들지 않고 중립을 유지한다.", "score": 80},
      {"id": "B", "text": "두 사람을 함께 불러 대화로 해결하도록 돕는다.", "score": 100},
      {"id": "C", "text": "팀장님께 상황을 알리고 조언을 구한다.", "score": 90}
    ],
    "learningPoint": "갈등 상황에서는 당사자들이 직접 대화하도록 돕는 것이 바람직합니다."
  },
  {
    "id": "CARD-007",
    "title": "업무 과중",
    "situation": "최근 3개월간 야근이 계속되고 있고, 체력적으로 한계를 느끼고 있습니다. 하지만 팀 전체가 바쁜 상황입니다.",
    "choices": [
      {"id": "A", "text": "팀장님과 면담을 신청해 상황을 솔직하게 이야기한다.", "score": 100},
      {"id": "B", "text": "좀 더 버텨보며 프로젝트가 끝나길 기다린다.", "score": 80},
      {"id": "C", "text": "업무 우선순위를 재조정해 핵심 업무에 집중한다.", "score": 90}
    ],
    "learningPoint": "번아웃을 예방하기 위해 적극적으로 소통하는 것이 중요합니다."
  },
  {
    "id": "CARD-008",
    "title": "신입사원 교육",
    "situation": "당신에게 신입사원 교육이 맡겨졌습니다. 하지만 본업도 바쁜 상황에서 시간을 내기 어렵습니다.",
    "choices": [
      {"id": "A", "text": "교육 자료를 만들어 신입이 스스로 학습하도록 한다.", "score": 80},
      {"id": "B", "text": "점심시간이나 출근 전 시간을 활용해 교육한다.", "score": 90},
      {"id": "C", "text": "업무를 조금씩 함께 하면서 OJT 방식으로 교육한다.", "score": 100}
    ],
    "learningPoint": "효율적인 교육 방법을 찾으면서도 신입의 성장을 도울 수 있습니다."
  },
  {
    "id": "CARD-009",
    "title": "아이디어 도용",
    "situation": "회의에서 당신이 제안했던 아이디어를 다른 팀원이 자기 것처럼 발표했습니다.",
    "choices": [
      {"id": "A", "text": "회의 중에 원래 내 아이디어였음을 밝힌다.", "score": 80},
      {"id": "B", "text": "회의 후 해당 팀원에게 따로 이야기한다.", "score": 100},
      {"id": "C", "text": "이번은 넘어가고 다음부터 기록을 남긴다.", "score": 90}
    ],
    "learningPoint": "상황에 따라 적절한 타이밍과 방법으로 권리를 주장하는 것이 중요합니다."
  },
  {
    "id": "CARD-010",
    "title": "부정확한 지시",
    "situation": "팀장님의 업무 지시가 명확하지 않아 어떻게 진행해야 할지 모르겠습니다.",
    "choices": [
      {"id": "A", "text": "내가 이해한 대로 진행하고 중간에 확인받는다.", "score": 90},
      {"id": "B", "text": "바로 팀장님께 다시 구체적으로 질문한다.", "score": 100},
      {"id": "C", "text": "비슷한 업무를 했던 선배에게 조언을 구한다.", "score": 80}
    ],
    "learningPoint": "불확실한 상황에서는 확인하는 것이 재작업을 줄이는 방법입니다."
  },
  {
    "id": "CARD-011",
    "title": "이메일 실수",
    "situation": "중요한 이메일을 잘못된 수신자에게 보내버렸습니다. 내용에는 민감한 정보가 포함되어 있습니다.",
    "choices": [
      {"id": "A", "text": "즉시 상사에게 보고하고 대응 방안을 논의한다.", "score": 100},
      {"id": "B", "text": "잘못 받은 수신자에게 삭제를 요청하는 메일을 보낸다.", "score": 80},
      {"id": "C", "text": "정보보안팀에 먼저 연락해 조치를 요청한다.", "score": 90}
    ],
    "learningPoint": "실수 발생 시 빠르게 보고하고 적절한 부서와 협력하는 것이 피해를 최소화합니다."
  },
  {
    "id": "CARD-012",
    "title": "부당한 평가",
    "situation": "인사평가 결과가 나왔는데, 당신이 기대했던 것보다 훨씬 낮습니다. 평가 기준이 불공정했다고 느껴집니다.",
    "choices": [
      {"id": "A", "text": "팀장님께 면담을 신청해 평가 근거를 물어본다.", "score": 100},
      {"id": "B", "text": "인사팀에 공식적으로 이의를 제기한다.", "score": 80},
      {"id": "C", "text": "다음 평가에서 더 노력하기로 하고 넘어간다.", "score": 90}
    ],
    "learningPoint": "평가에 대해 궁금한 점은 건설적으로 질문하는 것이 성장에 도움이 됩니다."
  },
  {
    "id": "CARD-013",
    "title": "회식 불참",
    "situation": "팀 회식이 잡혔는데, 개인 사정으로 참석하기 어렵습니다. 팀 분위기상 불참하면 눈치가 보입니다.",
    "choices": [
      {"id": "A", "text": "사정을 솔직하게 말하고 양해를 구한다.", "score": 100},
      {"id": "B", "text": "잠깐이라도 참석하고 일찍 빠진다.", "score": 90},
      {"id": "C", "text": "다음 회식에는 꼭 참석하겠다고 약속한다.", "score": 80}
    ],
    "learningPoint": "솔직한 커뮤니케이션이 오히려 신뢰를 쌓는 방법입니다."
  },
  {
    "id": "CARD-014",
    "title": "타 부서 협업",
    "situation": "프로젝트를 위해 타 부서와 협업해야 하는데, 해당 부서가 비협조적입니다.",
    "choices": [
      {"id": "A", "text": "상대 부서장에게 공식적으로 협조를 요청한다.", "score": 80},
      {"id": "B", "text": "상대 부서 실무자와 직접 만나 상황을 설명한다.", "score": 100},
      {"id": "C", "text": "우리 팀장님을 통해 위에서 해결하도록 한다.", "score": 90}
    ],
    "learningPoint": "부서 간 협업은 관계 구축이 중요합니다."
  },
  {
    "id": "CARD-015",
    "title": "회의 중 졸음",
    "situation": "중요한 회의 중에 너무 졸려서 집중이 안 됩니다.",
    "choices": [
      {"id": "A", "text": "잠깐 화장실에 다녀와서 정신을 차린다.", "score": 90},
      {"id": "B", "text": "적극적으로 발언하면서 참여도를 높인다.", "score": 100},
      {"id": "C", "text": "커피를 마시며 버텨본다.", "score": 80}
    ],
    "learningPoint": "자기 관리도 프로페셔널리즘의 일부입니다."
  },
  {
    "id": "CARD-016",
    "title": "업무 분배 불균형",
    "situation": "특정 팀원에게만 업무가 몰리고 있고, 불만의 목소리가 들립니다.",
    "choices": [
      {"id": "A", "text": "팀장님께 업무 재분배를 건의한다.", "score": 90},
      {"id": "B", "text": "힘든 팀원의 업무를 일부 돕는다.", "score": 100},
      {"id": "C", "text": "팀 미팅에서 공개적으로 논의하자고 제안한다.", "score": 80}
    ],
    "learningPoint": "팀의 문제는 팀 전체가 함께 해결하는 것이 바람직합니다."
  },
  {
    "id": "CARD-017",
    "title": "프레젠테이션 실패",
    "situation": "중요한 프레젠테이션에서 예상치 못한 질문에 제대로 답변하지 못했습니다.",
    "choices": [
      {"id": "A", "text": "회의 후 추가 자료와 함께 답변을 이메일로 보낸다.", "score": 100},
      {"id": "B", "text": "다음 기회에 더 잘하기로 마음먹고 넘어간다.", "score": 80},
      {"id": "C", "text": "상사에게 피드백을 요청하고 개선점을 찾는다.", "score": 90}
    ],
    "learningPoint": "실수는 성장의 기회입니다. 중요한 것은 대응 방법입니다."
  },
  {
    "id": "CARD-018",
    "title": "보안 위반 목격",
    "situation": "동료가 회사 보안 정책을 위반하는 것을 목격했습니다.",
    "choices": [
      {"id": "A", "text": "동료에게 직접 위험성을 알리고 중단을 권유한다.", "score": 100},
      {"id": "B", "text": "익명으로 보안팀에 신고한다.", "score": 80},
      {"id": "C", "text": "상사에게 상황을 보고한다.", "score": 90}
    ],
    "learningPoint": "보안은 모두의 책임입니다. 적절한 방법으로 대응해야 합니다."
  },
  {
    "id": "CARD-019",
    "title": "연봉 협상",
    "situation": "연봉 협상 시기가 다가왔습니다. 현재 연봉이 시장 평균보다 낮다고 느껴집니다.",
    "choices": [
      {"id": "A", "text": "시장 조사 데이터를 준비해서 협상에 임한다.", "score": 90},
      {"id": "B", "text": "성과를 정리해서 기여도를 어필한다.", "score": 100},
      {"id": "C", "text": "이직 제안을 협상 카드로 활용한다.", "score": 80}
    ],
    "learningPoint": "연봉 협상은 데이터와 성과를 바탕으로 논리적으로 접근해야 합니다."
  },
  {
    "id": "CARD-020",
    "title": "신기술 도입",
    "situation": "새로운 기술/도구를 도입하자고 제안했지만, 팀의 반응이 부정적입니다.",
    "choices": [
      {"id": "A", "text": "작은 규모의 파일럿 프로젝트로 먼저 검증한다.", "score": 100},
      {"id": "B", "text": "도입 시 얻을 수 있는 이점을 구체적으로 설명한다.", "score": 90},
      {"id": "C", "text": "팀의 의견을 존중하고 제안을 철회한다.", "score": 80}
    ],
    "learningPoint": "변화를 이끌 때는 작은 성공 사례로 신뢰를 쌓는 것이 효과적입니다."
  },
  {
    "id": "CARD-021",
    "title": "원격 근무 소통",
    "situation": "원격 근무 중 팀원들과의 소통이 원활하지 않아 업무에 지장이 생기고 있습니다.",
    "choices": [
      {"id": "A", "text": "정기적인 화상 스탠드업 미팅을 제안한다.", "score": 100},
      {"id": "B", "text": "메신저를 더 적극적으로 활용해 소통을 늘린다.", "score": 90},
      {"id": "C", "text": "업무 진행 상황을 문서로 공유하는 시스템을 만든다.", "score": 80}
    ],
    "learningPoint": "원격 환경에서는 의도적인 소통 노력이 필요합니다."
  },
  {
    "id": "CARD-022",
    "title": "멘토링 요청",
    "situation": "업무 역량을 키우고 싶어 선배에게 멘토링을 요청하려고 합니다.",
    "choices": [
      {"id": "A", "text": "구체적인 목표와 기대사항을 정리해서 요청한다.", "score": 100},
      {"id": "B", "text": "비공식적으로 점심이나 커피 시간에 조언을 구한다.", "score": 90},
      {"id": "C", "text": "회사의 공식 멘토링 프로그램을 활용한다.", "score": 80}
    ],
    "learningPoint": "성장을 위해 적극적으로 도움을 요청하는 것은 좋은 태도입니다."
  },
  {
    "id": "CARD-023",
    "title": "실적 압박",
    "situation": "분기 실적 목표 달성이 어려워 보입니다. 팀 전체가 압박을 받고 있습니다.",
    "choices": [
      {"id": "A", "text": "현실적인 대안과 함께 상황을 보고한다.", "score": 100},
      {"id": "B", "text": "가능한 모든 방법을 동원해 목표 달성을 시도한다.", "score": 80},
      {"id": "C", "text": "다음 분기 계획을 포함한 회복 방안을 준비한다.", "score": 90}
    ],
    "learningPoint": "어려운 상황일수록 솔직한 소통과 대안 제시가 중요합니다."
  },
  {
    "id": "CARD-024",
    "title": "승진 경쟁",
    "situation": "같이 입사한 동기가 먼저 승진했습니다. 축하해야 하지만 복잡한 기분입니다.",
    "choices": [
      {"id": "A", "text": "진심으로 축하하고 나의 성장에 집중한다.", "score": 100},
      {"id": "B", "text": "상사에게 내가 부족한 점을 피드백 받는다.", "score": 90},
      {"id": "C", "text": "다른 기회나 경로를 탐색해본다.", "score": 80}
    ],
    "learningPoint": "다른 사람과의 비교보다 자신의 성장에 집중하는 것이 건강한 태도입니다."
  },
  {
    "id": "CARD-025",
    "title": "업무 인수인계",
    "situation": "담당자가 갑자기 퇴사해서 인수인계 없이 업무를 맡게 되었습니다.",
    "choices": [
      {"id": "A", "text": "관련 문서와 히스토리를 먼저 파악한다.", "score": 90},
      {"id": "B", "text": "해당 업무 관련자들에게 적극적으로 질문한다.", "score": 100},
      {"id": "C", "text": "상사에게 현실적인 학습 기간을 요청한다.", "score": 80}
    ],
    "learningPoint": "불완전한 인수인계 상황에서는 체계적인 학습 접근이 필요합니다."
  },
  {
    "id": "CARD-026",
    "title": "회의 지각",
    "situation": "중요한 회의에 5분 늦게 도착했습니다. 이미 회의가 시작된 상태입니다.",
    "choices": [
      {"id": "A", "text": "조용히 들어가 자리에 앉는다.", "score": 80},
      {"id": "B", "text": "간단히 사과하고 참석한다.", "score": 100},
      {"id": "C", "text": "회의 후 주관자에게 따로 사과한다.", "score": 90}
    ],
    "learningPoint": "작은 실수라도 적절한 사과는 신뢰를 유지하는 데 도움이 됩니다."
  },
  {
    "id": "CARD-027",
    "title": "크레딧 분배",
    "situation": "팀 프로젝트가 성공했는데, 특정 팀원의 기여도가 과대평가되고 있습니다.",
    "choices": [
      {"id": "A", "text": "팀 전체의 기여를 강조하는 발언을 한다.", "score": 100},
      {"id": "B", "text": "나중에 상사에게 실제 기여도를 설명한다.", "score": 80},
      {"id": "C", "text": "이번은 넘어가고 다음에 기록을 잘 남긴다.", "score": 90}
    ],
    "learningPoint": "공정한 인정은 팀 동기부여에 중요합니다."
  },
  {
    "id": "CARD-028",
    "title": "피드백 전달",
    "situation": "후배의 업무 결과물이 기대에 미치지 못합니다. 피드백을 줘야 할 것 같습니다.",
    "choices": [
      {"id": "A", "text": "구체적인 개선점과 함께 건설적으로 피드백한다.", "score": 100},
      {"id": "B", "text": "일단 직접 수정하고 나중에 설명해준다.", "score": 80},
      {"id": "C", "text": "좋은 점을 먼저 말하고 개선점을 부드럽게 전달한다.", "score": 90}
    ],
    "learningPoint": "효과적인 피드백은 구체적이고 건설적이어야 합니다."
  },
  {
    "id": "CARD-029",
    "title": "예산 초과",
    "situation": "프로젝트 예산이 예상보다 초과될 것 같습니다. 아직 경영진 보고 전입니다.",
    "choices": [
      {"id": "A", "text": "비용 절감 방안을 찾아 예산 내로 맞춘다.", "score": 80},
      {"id": "B", "text": "추가 예산의 필요성과 사유를 정리해 보고한다.", "score": 100},
      {"id": "C", "text": "우선순위를 조정해 핵심 기능에 집중한다.", "score": 90}
    ],
    "learningPoint": "예산 문제는 빠른 보고와 대안 제시가 중요합니다."
  },
  {
    "id": "CARD-030",
    "title": "건강 관리",
    "situation": "최근 건강 검진에서 스트레스 관련 이상 징후가 발견되었습니다.",
    "choices": [
      {"id": "A", "text": "업무량을 조절하고 생활 습관을 개선한다.", "score": 90},
      {"id": "B", "text": "상사에게 상황을 공유하고 업무 조정을 요청한다.", "score": 80},
      {"id": "C", "text": "전문의 상담을 받고 치료에 집중한다.", "score": 100}
    ],
    "learningPoint": "건강은 지속 가능한 성과의 기반입니다."
  },
  {
    "id": "CARD-031",
    "title": "윤리적 딜레마",
    "situation": "상사가 실적을 부풀려 보고하라고 지시했습니다. 이는 회사 윤리 기준에 어긋납니다.",
    "choices": [
      {"id": "A", "text": "정중하게 거절하고 사실대로 보고한다.", "score": 100},
      {"id": "B", "text": "윤리 핫라인에 익명으로 신고한다.", "score": 80},
      {"id": "C", "text": "더 높은 상사나 HR에 상담한다.", "score": 90}
    ],
    "learningPoint": "윤리적 기준은 어떤 상황에서도 지켜야 할 중요한 가치입니다."
  }
]
